[{"Dataset": "20NewsGroup", "Dataset Size": 16309, "Model": "NMF", "Params": {"num_topics": 10, "random_state": 42}, "Scores": {"npmi": 0.07804043612188058, "diversity": 0.78}, "Computation Time": 8.451842546463013}, {"Dataset": "20NewsGroup", "Dataset Size": 16309, "Model": "NMF", "Params": {"num_topics": 20, "random_state": 42}, "Scores": {"npmi": 0.09240221456230875, "diversity": 0.68}, "Computation Time": 9.799983263015747}, {"Dataset": "20NewsGroup", "Dataset Size": 16309, "Model": "NMF", "Params": {"num_topics": 30, "random_state": 42}, "Scores": {"npmi": 0.09349977841138706, "diversity": 0.6333333333333333}, "Computation Time": 11.856500148773193}, {"Dataset": "20NewsGroup", "Dataset Size": 16309, "Model": "NMF", "Params": {"num_topics": 40, "random_state": 42}, "Scores": {"npmi": 0.08449866905616772, "diversity": 0.6}, "Computation Time": 13.02953553199768}, {"Dataset": "20NewsGroup", "Dataset Size": 16309, "Model": "NMF", "Params": {"num_topics": 50, "random_state": 42}, "Scores": {"npmi": 0.08717203037891542, "diversity": 0.568}, "Computation Time": 15.159289121627808}]